agentci/cli/__init__.py
agentci-0.1.1.dist-info/METADATA
agentci-0.1.1.dist-info/WHEEL
agentci-0.1.1.dist-info/entry_points.txt
agentci-0.1.1.dist-info/licenses/LICENSE
agentci-0.1.1.dist-info/RECORD
