Metadata-Version: 2.4
Name: agentci
Version: 0.1.1
Summary: Agent CI command-line interface
Project-URL: Homepage, https://agent-ci.com
Project-URL: Repository, https://github.com/Agent-CI/cli.git
Project-URL: Issues, https://github.com/Agent-CI/cli/issues
Author-email: Agent CI <hello@agent-ci.com>, Travis Dent <root@a10k.co>
License: MIT
License-File: LICENSE
Keywords: agentci,agents,ci,cli,testing
Classifier: Development Status :: 3 - Alpha
Classifier: Intended Audience :: Developers
Classifier: Operating System :: OS Independent
Classifier: Programming Language :: Python :: 3
Classifier: Programming Language :: Python :: 3.11
Classifier: Programming Language :: Python :: 3.12
Requires-Python: >=3.11
Requires-Dist: agentci-client-config==0.1.0
